appfl/__init__.py
appfl/agent/__init__.py
appfl/agent/client.py
appfl/agent/server.py
appfl/algorithm/__init__.py
appfl/algorithm/aggregator/__init__.py
appfl/algorithm/aggregator/base_aggregator.py
appfl/algorithm/aggregator/fedadagrad_aggregator.py
appfl/algorithm/aggregator/fedadam_aggregator.py
appfl/algorithm/aggregator/fedasync_aggregator.py
appfl/algorithm/aggregator/fedavg_aggregator.py
appfl/algorithm/aggregator/fedavgm_aggregator.py
appfl/algorithm/aggregator/fedbuff_aggregator.py
appfl/algorithm/aggregator/fedcompass_aggregator.py
appfl/algorithm/aggregator/fedsb_aggregator.py
appfl/algorithm/aggregator/fedyogi_aggregator.py
appfl/algorithm/aggregator/iceadmm_aggregator.py
appfl/algorithm/aggregator/iiadmm_aggregator.py
appfl/algorithm/aggregator/vfl_aggregator.py
appfl/algorithm/scheduler/__init__.py
appfl/algorithm/scheduler/async_scheduler.py
appfl/algorithm/scheduler/base_scheduler.py
appfl/algorithm/scheduler/compass_scheduler.py
appfl/algorithm/scheduler/sync_scheduler.py
appfl/algorithm/trainer/__init__.py
appfl/algorithm/trainer/base_trainer.py
appfl/algorithm/trainer/fedsb_trainer.py
appfl/algorithm/trainer/iceadmm_trainer.py
appfl/algorithm/trainer/iiadmm_trainer.py
appfl/algorithm/trainer/monai_trainer.py
appfl/algorithm/trainer/vanilla_trainer.py
appfl/comm/__init__.py
appfl/comm/base/__init__.py
appfl/comm/base/base_server_communicator.py
appfl/comm/globus_compute/__init__.py
appfl/comm/globus_compute/globus_compute_client_communicator.py
appfl/comm/globus_compute/globus_compute_server_communicator.py
appfl/comm/globus_compute/utils/__init__.py
appfl/comm/globus_compute/utils/endpoint.py
appfl/comm/grpc/__init__.py
appfl/comm/grpc/_credentials.py
appfl/comm/grpc/auth.py
appfl/comm/grpc/authenticator.py
appfl/comm/grpc/channel.py
appfl/comm/grpc/grpc_client_communicator.py
appfl/comm/grpc/grpc_communicator_pb2.py
appfl/comm/grpc/grpc_communicator_pb2.pyi
appfl/comm/grpc/grpc_communicator_pb2_grpc.py
appfl/comm/grpc/grpc_server_communicator.py
appfl-2.0.0.dist-info/licenses/LICENSE
appfl-2.0.0.dist-info/METADATA
appfl-2.0.0.dist-info/WHEEL
appfl-2.0.0.dist-info/entry_points.txt
appfl-2.0.0.dist-info/top_level.txt
appfl-2.0.0.dist-info/RECORD
